stuff_saver-0.1.7.dist-info/METADATA
stuff_saver-0.1.7.dist-info/WHEEL
stuff_saver-0.1.7.dist-info/licenses/LICENSE
stuff_saver/__init__.py
stuff_saver/foo.py
stuff_saver/stuff_saver.py
stuff_saver/utils.py
stuff_saver-0.1.7.dist-info/RECORD
