Metadata-Version: 2.1
Name: stuff_saver
Version: 0.1.7
Summary: Just save stuffs
Keywords: python
Author-Email: Joris GUERRY <j@9h.gg>
License: MIT
Classifier: Programming Language :: Python :: 3
Classifier: Programming Language :: Python :: 3.8
Classifier: Programming Language :: Python :: 3.9
Classifier: Programming Language :: Python :: 3.10
Classifier: Programming Language :: Python :: 3.11
Classifier: Programming Language :: Python :: 3.12
Project-URL: Homepage, https://jorisgu.github.io/stuff-saver/
Project-URL: Repository, https://github.com/jorisgu/stuff-saver
Project-URL: Documentation, https://jorisgu.github.io/stuff-saver/
Requires-Python: <4.0,>=3.9
